geo_importer-0.1.0b22.dist-info/licenses/LICENSE
src/__init__.py
src/app_icon.png
src/main.py
src/core/__init__.py
src/core/constants.py
src/core/data_store.py
src/core/stats_processor.py
src/core/step_descriptions.py
src/core/steps.py
src/geodata/NUTS_2024_3.csv
src/geodata/NUTS_2024_3_old.csv
src/geodata/LAU/LAU2021/LAU.csv
src/geodata/LAU/LAU2022/LAU.csv
src/geodata/LAU/LAU2023/LAU.csv
src/geodata/LOR/LOR2007/LOR1.csv
src/geodata/LOR/LOR2007/LOR2.csv
src/geodata/LOR/LOR2007/LOR3.csv
src/geodata/LOR/LOR2019/LOR1.csv
src/geodata/LOR/LOR2019/LOR2.csv
src/geodata/LOR/LOR2019/LOR3.csv
src/geodata/LOR/LOR2021/LOR1.csv
src/geodata/LOR/LOR2021/LOR2.csv
src/geodata/LOR/LOR2021/LOR3.csv
src/geodata/NUTS/2024/2024_level_0.csv
src/geodata/NUTS/2024/2024_level_1.csv
src/geodata/NUTS/2024/2024_level_2.csv
src/geodata/NUTS/2024/2024_level_3.csv
src/geodata/NUTS/NUTS2016/NUTS0.csv
src/geodata/NUTS/NUTS2016/NUTS1.csv
src/geodata/NUTS/NUTS2016/NUTS2.csv
src/geodata/NUTS/NUTS2016/NUTS3.csv
src/geodata/NUTS/NUTS2021/NUTS0.csv
src/geodata/NUTS/NUTS2021/NUTS1.csv
src/geodata/NUTS/NUTS2021/NUTS2.csv
src/geodata/NUTS/NUTS2021/NUTS3.csv
src/geodata/NUTS/NUTS2024/NUTS0.csv
src/geodata/NUTS/NUTS2024/NUTS1.csv
src/geodata/NUTS/NUTS2024/NUTS2.csv
src/geodata/NUTS/NUTS2024/NUTS3.csv
src/geodata/NUTS/NUTS2024/dummy.csv
src/mapper/__init__.py
src/mapper/base/__init__.py
src/mapper/base/matcher_base.py
src/mapper/matchers/__init__.py
src/mapper/matchers/fuzzy_matcher.py
src/mapper/matchers/prefix_matcher.py
src/mapper/matchers/regex_matcher.py
src/mapper/matchers/unique_value_matcher.py
src/mapper/matchers/ui/fuzzy_matcher_ui.py
src/mapper/matchers/ui/prefix_matcher_ui.py
src/mapper/matchers/ui/regex_matcher_ui.py
src/mapper/matchers/ui/unique_value_matcher_ui.py
src/models/__init__.py
src/models/dataframe_model.py
src/views/__init__.py
src/views/auto_map/__init__.py
src/views/auto_map/mapping_window.py
src/views/auto_map/ui/mapping_ui.py
src/views/clean_data/__init__.py
src/views/clean_data/dataprep_helpers.py
geo_importer-0.1.0b22.dist-info/METADATA
geo_importer-0.1.0b22.dist-info/WHEEL
geo_importer-0.1.0b22.dist-info/entry_points.txt
geo_importer-0.1.0b22.dist-info/top_level.txt
geo_importer-0.1.0b22.dist-info/RECORD
